hooly_utils_kit/Formatters.py
hooly_utils_kit/Validators.py
hooly_utils_kit/__init__.py
tests/__init__.py
tests/test_formatters.py
tests/test_validators.py
hooly_utils_kit-0.0.3.dist-info/LICENSE
hooly_utils_kit-0.0.3.dist-info/METADATA
hooly_utils_kit-0.0.3.dist-info/WHEEL
hooly_utils_kit-0.0.3.dist-info/top_level.txt
hooly_utils_kit-0.0.3.dist-info/RECORD
