Metadata-Version: 2.1
Name: hooly-utils-kit
Version: 0.0.3
Summary: A small library for utils
Home-page: https://github.com/AFP-Capital/hooly-utils-kit-py
Author: David Erazo
Author-email: david.erazo@afpcapital.cl
License: UNKNOWN
Platform: UNKNOWN
Classifier: Programming Language :: Python :: 3
Classifier: License :: OSI Approved :: MIT License
Classifier: Operating System :: OS Independent
Requires-Python: >=3.6
